Workbook
Name SegmentaciónDeDatos_genres___Clean: #N/A
Name SegmentaciónDeDatos_Grupo_Edad: #N/A
Name SegmentaciónDeDatos_IMDb_Tier1: #N/A
Name SegmentaciónDeDatos_production_countries___Clean: #N/A
Name SegmentaciónDeDatos_type: #N/A
Name Timeline_Fecha_Timeline: #N/A

Sheet Datos limpios
A1: id | B1: title | C1: type | D1: description | E1: release_year | F1: age_certification | G1: runtime_HHMM | H1: runtime | I1: genres | J1: genres - Clean | K1: production_countries - Clean | L1: production_countries | M1: seasons | N1: imdb_id | O1: imdb_score | P1: imdb_votes | Q1: tmdb_popularity | R1: tmdb_score
A2: ts300399 | B2: Five Came Back: The Reference Films | C2: SHOW | D2: This collection includes 12 World War II-era propaganda films — many of which are graphic and offensive — discussed in the docuseries "Five Came Back." | E2: 1945 | F2: TV-MA | G2: 00:51 | H2: 51 | I2: ['documentation'] | J2: documentation | K2: US | L2: ['US'] | M2: 1.0 | Q2: 0.6
A3: tm84618 | B3: Taxi Driver | C3: MOVIE | D3: A mentally unstable Vietnam War veteran works as a night-time taxi driver in New York City where the perceived decadence and sleaze feed his urge for violent action. | E3: 1976 | F3: R | G3: 01:54 | H3: 114 | I3: ['drama', 'crime'] | J3: drama | K3: US | L3: ['US'] | N3: tt0075314 | O3: 8.2 | P3: 808582 | Q3: 40.965 | R3: 8.179
A4: tm84618 | B4: Taxi Driver | C4: MOVIE | D4: A mentally unstable Vietnam War veteran works as a night-time taxi driver in New York City where the perceived decadence and sleaze feed his urge for violent action. | E4: 1976 | F4: R | G4: 01:54 | H4: 114 | I4: ['drama', 'crime'] | J4: crime | K4: US | L4: ['US'] | N4: tt0075314 | O4: 8.2 | P4: 808582 | Q4: 40.965 | R4: 8.179
A5: tm154986 | B5: Deliverance | C5: MOVIE | D5: Intent on seeing the Cahulawassee River before it's turned into one huge lake, outdoor fanatic Lewis Medlock takes his friends on a river-rafting trip they'll never forget into the dangerous American back-country. | E5: 1972 | F5: R | G5: 01:49 | H5: 109 | I5: ['drama', 'action', 'thriller', 'european'] | J5: drama | K5: US | L5: ['US'] | N5: tt0068473 | O5: 7.7 | P5: 107673 | Q5: 10.01 | R5: 7.3
A6: tm154986 | B6: Deliverance | C6: MOVIE | D6: Intent on seeing the Cahulawassee River before it's turned into one huge lake, outdoor fanatic Lewis Medlock takes his friends on a river-rafting trip they'll never forget into the dangerous American back-country. | E6: 1972 | F6: R | G6: 01:49 | H6: 109 | I6: ['drama', 'action', 'thriller', 'european'] | J6: action | K6: US | L6: ['US'] | N6: tt0068473 | O6: 7.7 | P6: 107673 | Q6: 10.01 | R6: 7.3
A7: tm154986 | B7: Deliverance | C7: MOVIE | D7: Intent on seeing the Cahulawassee River before it's turned into one huge lake, outdoor fanatic Lewis Medlock takes his friends on a river-rafting trip they'll never forget into the dangerous American back-country. | E7: 1972 | F7: R | G7: 01:49 | H7: 109 | I7: ['drama', 'action', 'thriller', 'european'] | J7: thriller | K7: US | L7: ['US'] | N7: tt0068473 | O7: 7.7 | P7: 107673 | Q7: 10.01 | R7: 7.3
A8: tm154986 | B8: Deliverance | C8: MOVIE | D8: Intent on seeing the Cahulawassee River before it's turned into one huge lake, outdoor fanatic Lewis Medlock takes his friends on a river-rafting trip they'll never forget into the dangerous American back-country. | E8: 1972 | F8: R | G8: 01:49 | H8: 109 | I8: ['drama', 'action', 'thriller', 'european'] | J8: european | K8: US | L8: ['US'] | N8: tt0068473 | O8: 7.7 | P8: 107673 | Q8: 10.01 | R8: 7.3
A9: tm127384 | B9: Monty Python and the Holy Grail | C9: MOVIE | D9: King Arthur, accompanied by his squire, recruits his Knights of the Round Table, including Sir Bedevere the Wise, Sir Lancelot the Brave, Sir Robin the Not-Quite-So-Brave-As-Sir-Lancelot and Sir Galahad the Pure. On the way, Arthur battles the Black Knight who, despite having had all his limbs chopped off, insists he can still fight. They reach Camelot, but Arthur decides not to enter, as "it is a silly place". | E9: 1975 | F9: PG | G9: 01:31 | H9: 91 | I9: ['fantasy', 'action', 'comedy'] | J9: fantasy | K9: GB | L9: ['GB'] | N9: tt0071853 | O9: 8.2 | P9: 534486 | Q9: 15.461 | R9: 7.811
A10: tm127384 | B10: Monty Python and the Holy Grail | C10: MOVIE | D10: King Arthur, accompanied by his squire, recruits his Knights of the Round Table, including Sir Bedevere the Wise, Sir Lancelot the Brave, Sir Robin the Not-Quite-So-Brave-As-Sir-Lancelot and Sir Galahad the Pure. On the way, Arthur battles the Black Knight who, despite having had all his limbs chopped off, insists he can still fight. They reach Camelot, but Arthur decides not to enter, as "it is a silly place". | E10: 1975 | F10: PG | G10: 01:31 | H10: 91 | I10: ['fantasy', 'action', 'comedy'] | J10: action | K10: GB | L10: ['GB'] | N10: tt0071853 | O10: 8.2 | P10: 534486 | Q10: 15.461 | R10: 7.811
A11: tm127384 | B11: Monty Python and the Holy Grail | C11: MOVIE | D11: King Arthur, accompanied by his squire, recruits his Knights of the Round Table, including Sir Bedevere the Wise, Sir Lancelot the Brave, Sir Robin the Not-Quite-So-Brave-As-Sir-Lancelot and Sir Galahad the Pure. On the way, Arthur battles the Black Knight who, despite having had all his limbs chopped off, insists he can still fight. They reach Camelot, but Arthur decides not to enter, as "it is a silly place". | E11: 1975 | F11: PG | G11: 01:31 | H11: 91 | I11: ['fantasy', 'action', 'comedy'] | J11: comedy | K11: GB | L11: ['GB'] | N11: tt0071853 | O11: 8.2 | P11: 534486 | Q11: 15.461 | R11: 7.811
A12: tm120801 | B12: The Dirty Dozen | C12: MOVIE | D12: 12 American military prisoners in World War II are ordered to infiltrate a well-guarded enemy château and kill the Nazi officers vacationing there. The soldiers, most of whom are facing death sentences for a variety of violent crimes, agree to the mission and the possible commuting of their sentences. | E12: 1967 | F12: NO INFORMADO | G12: 02:30 | H12: 150 | I12: ['war', 'action'] | J12: war | K12: GB | L12: ['GB', 'US'] | N12: tt0061578 | O12: 7.7 | P12: 72662 | Q12: 20.398 | R12: 7.6
A13: tm120801 | B13: The Dirty Dozen | C13: MOVIE | D13: 12 American military prisoners in World War II are ordered to infiltrate a well-guarded enemy château and kill the Nazi officers vacationing there. The soldiers, most of whom are facing death sentences for a variety of violent crimes, agree to the mission and the possible commuting of their sentences. | E13: 1967 | F13: NO INFORMADO | G13: 02:30 | H13: 150 | I13: ['war', 'action'] | J13: war | K13: US | L13: ['GB', 'US'] | N13: tt0061578 | O13: 7.7 | P13: 72662 | Q13: 20.398 | R13: 7.6
A14: tm120801 | B14: The Dirty Dozen | C14: MOVIE | D14: 12 American military prisoners in World War II are ordered to infiltrate a well-guarded enemy château and kill the Nazi officers vacationing there. The soldiers, most of whom are facing death sentences for a variety of violent crimes, agree to the mission and the possible commuting of their sentences. | E14: 1967 | F14: NO INFORMADO | G14: 02:30 | H14: 150 | I14: ['war', 'action'] | J14: action | K14: GB | L14: ['GB', 'US'] | N14: tt0061578 | O14: 7.7 | P14: 72662 | Q14: 20.398 | R14: 7.6
A15: tm120801 | B15: The Dirty Dozen | C15: MOVIE | D15: 12 American military prisoners in World War II are ordered to infiltrate a well-guarded enemy château and kill the Nazi officers vacationing there. The soldiers, most of whom are facing death sentences for a variety of violent crimes, agree to the mission and the possible commuting of their sentences. | E15: 1967 | F15: NO INFORMADO | G15: 02:30 | H15: 150 | I15: ['war', 'action'] | J15: action | K15: US | L15: ['GB', 'US'] | N15: tt0061578 | O15: 7.7 | P15: 72662 | Q15: 20.398 | R15: 7.6
A16: ts22164 | B16: Monty Python's Flying Circus | C16: SHOW | D16: A British sketch comedy series with the shows being composed of surreality, risqué or innuendo-laden humour, sight gags and observational sketches without punchlines. | E16: 1969 | F16: TV-14 | G16: 00:30 | H16: 30 | I16: ['comedy', 'european'] | J16: comedy | K16: GB | L16: ['GB'] | M16: 4.0 | N16: tt0063929 | O16: 8.8 | P16: 73424 | Q16: 17.617 | R16: 8.306
A17: ts22164 | B17: Monty Python's Flying Circus | C17: SHOW | D17: A British sketch comedy series with the shows being composed of surreality, risqué or innuendo-laden humour, sight gags and observational sketches without punchlines. | E17: 1969 | F17: TV-14 | G17: 00:30 | H17: 30 | I17: ['comedy', 'european'] | J17: european | K17: GB | L17: ['GB'] | M17: 4.0 | N17: tt0063929 | O17: 8.8 | P17: 73424 | Q17: 17.617 | R17: 8.306
A18: tm70993 | B18: Life of Brian | C18: MOVIE | D18: Brian Cohen is an average young Jewish man, but through a series of ridiculous events, he gains a reputation as the Messiah. When he's not dodging his followers or being scolded by his shrill mother, the hapless Brian has to contend with the pompous Pontius Pilate and acronym-obsessed members of a separatist movement. Rife with Monty Python's signature absurdity, the tale finds Brian's life paralleling Biblical lore, albeit with many more laughs. | E18: 1979 | F18: R | G18: 01:34 | H18: 94 | I18: ['comedy'] | J18: comedy | K18: GB | L18: ['GB'] | N18: tt0079470 | O18: 8 | P18: 395024 | Q18: 17.77 | R18: 7.8
A19: tm14873 | B19: Dirty Harry | C19: MOVIE | D19: When a madman dubbed 'Scorpio' terrorizes San Francisco, hard-nosed cop, Harry Callahan – famous for his take-no-prisoners approach to law enforcement – is tasked with hunting down the psychopath. Harry eventually collars Scorpio in the process of rescuing a kidnap victim, only to see him walk on technicalities. Now, the maverick detective is determined to nail the maniac himself. | E19: 1971 | F19: R | G19: 01:42 | H19: 102 | I19: ['thriller', 'action', 'crime'] | J19: thriller | K19: US | L19: ['US'] | N19: tt0066999 | O19: 7.7 | P19: 155051 | Q19: 12.817 | R19: 7.5
A20: tm14873 | B20: Dirty Harry | C20: MOVIE | D20: When a madman dubbed 'Scorpio' terrorizes San Francisco, hard-nosed cop, Harry Callahan – famous for his take-no-prisoners approach to law enforcement – is tasked with hunting down the psychopath. Harry eventually collars Scorpio in the process of rescuing a kidnap victim, only to see him walk on technicalities. Now, the maverick detective is determined to nail the maniac himself. | E20: 1971 | F20: R | G20: 01:42 | H20: 102 | I20: ['thriller', 'action', 'crime'] | J20: action | K20: US | L20: ['US'] | N20: tt0066999 | O20: 7.7 | P20: 155051 | Q20: 12.817 | R20: 7.5
A21: tm14873 | B21: Dirty Harry | C21: MOVIE | D21: When a madman dubbed 'Scorpio' terrorizes San Francisco, hard-nosed cop, Harry Callahan – famous for his take-no-prisoners approach to law enforcement – is tasked with hunting down the psychopath. Harry eventually collars Scorpio in the process of rescuing a kidnap victim, only to see him walk on technicalities. Now, the maverick detective is determined to nail the maniac himself. | E21: 1971 | F21: R | G21: 01:42 | H21: 102 | I21: ['thriller', 'action', 'crime'] | J21: crime | K21: US | L21: ['US'] | N21: tt0066999 | O21: 7.7 | P21: 155051 | Q21: 12.817 | R21: 7.5
A22: tm119281 | B22: Bonnie and Clyde | C22: MOVIE | D22: In the 1930s, bored waitress Bonnie Parker falls in love with an ex-con named Clyde Barrow and together they start a violent crime spree through the country, stealing cars and robbing banks. | E22: 1967 | F22: R | G22: 01:50 | H22: 110 | I22: ['crime', 'drama', 'action'] | J22: crime | K22: US | L22: ['US'] | N22: tt0061418 | O22: 7.7 | P22: 112048 | Q22: 15.687 | R22: 7.5
A23: tm119281 | B23: Bonnie and Clyde | C23: MOVIE | D23: In the 1930s, bored waitress Bonnie Parker falls in love with an ex-con named Clyde Barrow and together they start a violent crime spree through the country, stealing cars and robbing banks. | E23: 1967 | F23: R | G23: 01:50 | H23: 110 | I23: ['crime', 'drama', 'action'] | J23: drama | K23: US | L23: ['US'] | N23: tt0061418 | O23: 7.7 | P23: 112048 | Q23: 15.687 | R23: 7.5
A24: tm119281 | B24: Bonnie and Clyde | C24: MOVIE | D24: In the 1930s, bored waitress Bonnie Parker falls in love with an ex-con named Clyde Barrow and together they start a violent crime spree through the country, stealing cars and robbing banks. | E24: 1967 | F24: R | G24: 01:50 | H24: 110 | I24: ['crime', 'drama', 'action'] | J24: action | K24: US | L24: ['US'] | N24: tt0061418 | O24: 7.7 | P24: 112048 | Q24: 15.687 | R24: 7.5
A25: tm98978 | B25: The Blue Lagoon | C25: MOVIE | D25: Two small children and a ship's cook survive a shipwreck and find safety on an idyllic tropical island. Soon, however, the cook dies and the young boy and girl are left on their own. Days become years and Emmeline and Richard make a home for themselves surrounded by exotic creatures and nature's beauty. But will they ever see civilization again? | E25: 1980 | F25: R | G25: 01:44 | H25: 104 | I25: ['romance', 'action', 'drama'] | J25: romance | K25: US | L25: ['US'] | N25: tt0080453 | O25: 5.8 | P25: 69844 | Q25: 50.324 | R25: 6.156
A26: tm98978 | B26: The Blue Lagoon | C26: MOVIE | D26: Two small children and a ship's cook survive a shipwreck and find safety on an idyllic tropical island. Soon, however, the cook dies and the young boy and girl are left on their own. Days become years and Emmeline and Richard make a home for themselves surrounded by exotic creatures and nature's beauty. But will they ever see civilization again? | E26: 1980 | F26: R | G26: 01:44 | H26: 104 | I26: ['romance', 'action', 'drama'] | J26: action | K26: US | L26: ['US'] | N26: tt0080453 | O26: 5.8 | P26: 69844 | Q26: 50.324 | R26: 6.156
A27: tm98978 | B27: The Blue Lagoon | C27: MOVIE | D27: Two small children and a ship's cook survive a shipwreck and find safety on an idyllic tropical island. Soon, however, the cook dies and the young boy and girl are left on their own. Days become years and Emmeline and Richard make a home for themselves surrounded by exotic creatures and nature's beauty. But will they ever see civilization again? | E27: 1980 | F27: R | G27: 01:44 | H27: 104 | I27: ['romance', 'action', 'drama'] | J27: drama | K27: US | L27: ['US'] | N27: tt0080453 | O27: 5.8 | P27: 69844 | Q27: 50.324 | R27: 6.156
A28: tm44204 | B28: The Guns of Navarone | C28: MOVIE | D28: A team of allied saboteurs are assigned an impossible mission: infiltrate an impregnable Nazi-held island and destroy the two enormous long-range field guns that prevent the rescue of 2,000 trapped British soldiers. | E28: 1961 | F28: NO INFORMADO | G28: 02:38 | H28: 158 | I28: ['action', 'drama', 'war'] | J28: action | K28: GB | L28: ['GB', 'US'] | N28: tt0054953 | O28: 7.5 | P28: 50748 | Q28: 13.844 | R28: 7.3
A29: tm44204 | B29: The Guns of Navarone | C29: MOVIE | D29: A team of allied saboteurs are assigned an impossible mission: infiltrate an impregnable Nazi-held island and destroy the two enormous long-range field guns that prevent the rescue of 2,000 trapped British soldiers. | E29: 1961 | F29: NO INFORMADO | G29: 02:38 | H29: 158 | I29: ['action', 'drama', 'war'] | J29: action | K29: US | L29: ['GB', 'US'] | N29: tt0054953 | O29: 7.5 | P29: 50748 | Q29: 13.844 | R29: 7.3
... A107: tm16812 | B107: Bandie | C107: MOVIE | D107: Maharaj Brajbhan lives a wealthy lifestyle in Bharatpur, India along with his wife, Badi Rani, but have been unable to conceive for Bharatpur, and have no choice but to leave it's reigns with Brajban's widowed cousin, Vikram, and his son, Kanchan. When Vikram finds out that Badi Rani is pregnant, he plots to first sully her character by having her abducted, then shunned by the Maharaj, and then decides to have her killed. But her killer has a change of heart and lets her live. She gives birth to a son, names him Bhola, and starts living a simple lifestyle in a Mandir with the help of it's Poojary. Years later Vikram finds out she is alive and kills her, as well the Poojary and the Poojary's son. Bhola witnesses this, manages to escape, starts to live with a poor widow, grows up uneducated, and makes a living through crime. | E107: 1978 | F107: NO INFORMADO | G107: 02:21 | H107: 141 | I107: ['drama', 'action', 'romance'] | J107: romance | K107: IN | L107: ['IN'] | N107: tt1219315 | O107: 4.4 | P107: 35 | Q107: 1.166 | R107: 6
A108: ts20681 | B108: Seinfeld | C108: SHOW | D108: A stand-up comedian and his three offbeat friends weather the pitfalls and payoffs of life in New York City in the '90s. It's a show about nothing. | E108: 1989 | F108: TV-PG | G108: 00:24 | H108: 24 | I108: ['comedy'] | J108: comedy | K108: US | L108: ['US'] | M108: 9.0 | N108: tt0098904 | O108: 8.9 | P108: 308824 | Q108: 130.213 | R108: 8.301
A109: tm155787 | B109: GoodFellas | C109: MOVIE | D109: The true story of Henry Hill, a half-Irish, half-Sicilian Brooklyn kid who is adopted by neighbourhood gangsters at an early age and climbs the ranks of a Mafia family under the guidance of Jimmy Conway. | E109: 1990 | F109: R | G109: 02:25 | H109: 145 | I109: ['drama', 'crime'] | J109: drama | K109: US | L109: ['US'] | N109: tt0099685 | O109: 8.7 | P109: 1131681 | Q109: 50.387 | R109: 8.463
A110: tm155787 | B110: GoodFellas | C110: MOVIE | D110: The true story of Henry Hill, a half-Irish, half-Sicilian Brooklyn kid who is adopted by neighbourhood gangsters at an early age and climbs the ranks of a Mafia family under the guidance of Jimmy Conway. | E110: 1990 | F110: R | G110: 02:25 | H110: 145 | I110: ['drama', 'crime'] | J110: crime | K110: US | L110: ['US'] | N110: tt0099685 | O110: 8.7 | P110: 1131681 | Q110: 50.387 | R110: 8.463
A111: tm22327 | B111: Full Metal Jacket | C111: MOVIE | D111: A pragmatic U.S. Marine observes the dehumanizing effects the U.S.-Vietnam War has on his fellow recruits from their brutal boot camp training to the bloody street fighting in Hue. | E111: 1987 | F111: R | G111: 01:57 | H111: 117 | I111: ['war', 'drama'] | J111: war | K111: US | L111: ['US', 'GB'] | N111: tt0093058 | O111: 8.3 | P111: 729274 | Q111: 32.937 | R111: 8.1
A112: tm22327 | B112: Full Metal Jacket | C112: MOVIE | D112: A pragmatic U.S. Marine observes the dehumanizing effects the U.S.-Vietnam War has on his fellow recruits from their brutal boot camp training to the bloody street fighting in Hue. | E112: 1987 | F112: R | G112: 01:57 | H112: 117 | I112: ['war', 'drama'] | J112: war | K112: GB | L112: ['US', 'GB'] | N112: tt0093058 | O112: 8.3 | P112: 729274 | Q112: 32.937 | R112: 8.1
A113: tm22327 | B113: Full Metal Jacket | C113: MOVIE | D113: A pragmatic U.S. Marine observes the dehumanizing effects the U.S.-Vietnam War has on his fellow recruits from their brutal boot camp training to the bloody street fighting in Hue. | E113: 1987 | F113: R | G113: 01:57 | H113: 117 | I113: ['war', 'drama'] | J113: drama | K113: US | L113: ['US', 'GB'] | N113: tt0093058 | O113: 8.3 | P113: 729274 | Q113: 32.937 | R113: 8.1
A114: tm22327 | B114: Full Metal Jacket | C114: MOVIE | D114: A pragmatic U.S. Marine observes the dehumanizing effects the U.S.-Vietnam War has on his fellow recruits from their brutal boot camp training to the bloody street fighting in Hue. | E114: 1987 | F114: R | G114: 01:57 | H114: 117 | I114: ['war', 'drama'] | J114: drama | K114: GB | L114: ['US', 'GB'] | N114: tt0093058 | O114: 8.3 | P114: 729274 | Q114: 32.937 | R114: 8.1
A115: tm180542 | B115: Once Upon a Time in America | C115: MOVIE | D115: A former Prohibition-era Jewish gangster returns to the Lower East Side of Manhattan over thirty years later, where he once again must confront the ghosts and regrets of his old life. | E115: 1984 | F115: R | G115: 02:19 | H115: 139 | I115: ['crime', 'drama', 'european'] | J115: crime | K115: US | L115: ['US', 'IT'] | N115: tt0087843 | O115: 8.3 | P115: 345714 | Q115: 28.937 | R115: 8.453
A116: tm180542 | B116: Once Upon a Time in America | C116: MOVIE | D116: A former Prohibition-era Jewish gangster returns to the Lower East Side of Manhattan over thirty years later, where he once again must confront the ghosts and regrets of his old life. | E116: 1984 | F116: R | G116: 02:19 | H116: 139 | I116: ['crime', 'drama', 'european'] | J116: crime | K116: IT | L116: ['US', 'IT'] | N116: tt0087843 | O116: 8.3 | P116: 345714 | Q116: 28.937 | R116: 8.453
A117: tm180542 | B117: Once Upon a Time in America | C117: MOVIE | D117: A former Prohibition-era Jewish gangster returns to the Lower East Side of Manhattan over thirty years later, where he once again must confront the ghosts and regrets of his old life. | E117: 1984 | F117: R | G117: 02:19 | H117: 139 | I117: ['crime', 'drama', 'european'] | J117: drama | K117: US | L117: ['US', 'IT'] | N117: tt0087843 | O117: 8.3 | P117: 345714 | Q117: 28.937 | R117: 8.453
A118: tm180542 | B118: Once Upon a Time in America | C118: MOVIE | D118: A former Prohibition-era Jewish gangster returns to the Lower East Side of Manhattan over thirty years later, where he once again must confront the ghosts and regrets of his old life. | E118: 1984 | F118: R | G118: 02:19 | H118: 139 | I118: ['crime', 'drama', 'european'] | J118: drama | K118: IT | L118: ['US', 'IT'] | N118: tt0087843 | O118: 8.3 | P118: 345714 | Q118: 28.937 | R118: 8.453
A119: tm180542 | B119: Once Upon a Time in America | C119: MOVIE | D119: A former Prohibition-era Jewish gangster returns to the Lower East Side of Manhattan over thirty years later, where he once again must confront the ghosts and regrets of his old life. | E119: 1984 | F119: R | G119: 02:19 | H119: 139 | I119: ['crime', 'drama', 'european'] | J119: european | K119: US | L119: ['US', 'IT'] | N119: tt0087843 | O119: 8.3 | P119: 345714 | Q119: 28.937 | R119: 8.453
A120: tm180542 | B120: Once Upon a Time in America | C120: MOVIE | D120: A former Prohibition-era Jewish gangster returns to the Lower East Side of Manhattan over thirty years later, where he once again must confront the ghosts and regrets of his old life. | E120: 1984 | F120: R | G120: 02:19 | H120: 139 | I120: ['crime', 'drama', 'european'] | J120: european | K120: IT | L120: ['US', 'IT'] | N120: tt0087843 | O120: 8.3 | P120: 345714 | Q120: 28.937 | R120: 8.453
... A133: tm54450 | B133: Christine | C133: MOVIE | D133: Geeky student Arnie Cunningham falls for Christine, a rusty 1958 Plymouth Fury, and becomes obsessed with restoring the classic automobile to her former glory. As the car changes, so does Arnie, whose newfound confidence turns to arrogance behind the wheel of his exotic beauty. Arnie's girlfriend Leigh and best friend Dennis reach out to him, only to be met by a Fury like no other. | E133: 1983 | F133: R | G133: 01:50 | H133: 110 | I133: ['horror', 'thriller', 'european'] | J133: european | K133: US | L133: ['US'] | N133: tt0085333 | O133: 6.7 | P133: 81922 | Q133: 23.418 | R133: 6.8
A134: ts22082 | B134: Knight Rider | C134: SHOW | D134: Michael Long, an undercover police officer, is shot while investigating a case and left for dead by his assailants. He is rescued by Wilton Knight, a wealthy, dying millionaire and inventor who arranges life-saving surgery, including a new face and a new identity--that of Michael Knight. Michael is then given a special computerized and indestructible car called the Knight Industries Two Thousand (nicknamed KITT), and a mission: apprehend criminals who are beyond the reach of the law. The series depicts Michael's exploits as he and KITT battle the forces of evil on behalf of the Foundation for Law and Government. | E134: 1982 | F134: TV-PG | G134: 00:51 | H134: 51 | I134: ['scifi', 'action', 'crime', 'drama'] | J134: scifi | K134: US | L134: ['US'] | M134: 4.0 | N134: tt0083437 | O134: 6.9 | P134: 34115 | Q134: 50.267 | R134: 7.5
A135: ts22082 | B135: Knight Rider | C135: SHOW | D135: Michael Long, an undercover police officer, is shot while investigating a case and left for dead by his assailants. He is rescued by Wilton Knight, a wealthy, dying millionaire and inventor who arranges life-saving surgery, including a new face and a new identity--that of Michael Knight. Michael is then given a special computerized and indestructible car called the Knight Industries Two Thousand (nicknamed KITT), and a mission: apprehend criminals who are beyond the reach of the law. The series depicts Michael's exploits as he and KITT battle the forces of evil on behalf of the Foundation for Law and Government. | E135: 1982 | F135: TV-PG | G135: 00:51 | H135: 51 | I135: ['scifi', 'action', 'crime', 'drama'] | J135: action | K135: US | L135: ['US'] | M135: 4.0 | N135: tt0083437 | O135: 6.9 | P135: 34115 | Q135: 50.267 | R135: 7.5
A136: ts22082 | B136: Knight Rider | C136: SHOW | D136: Michael Long, an undercover police officer, is shot while investigating a case and left for dead by his assailants. He is rescued by Wilton Knight, a wealthy, dying millionaire and inventor who arranges life-saving surgery, including a new face and a new identity--that of Michael Knight. Michael is then given a special computerized and indestructible car called the Knight Industries Two Thousand (nicknamed KITT), and a mission: apprehend criminals who are beyond the reach of the law. The series depicts Michael's exploits as he and KITT battle the forces of evil on behalf of the Foundation for Law and Government. | E136: 1982 | F136: TV-PG | G136: 00:51 | H136: 51 | I136: ['scifi', 'action', 'crime', 'drama'] | J136: crime | K136: US | L136: ['US'] | M136: 4.0 | N136: tt0083437 | O136: 6.9 | P136: 34115 | Q136: 50.267 | R136: 7.5
A137: ts22082 | B137: Knight Rider | C137: SHOW | D137: Michael Long, an undercover police officer, is shot while investigating a case and left for dead by his assailants. He is rescued by Wilton Knight, a wealthy, dying millionaire and inventor who arranges life-saving surgery, including a new face and a new identity--that of Michael Knight. Michael is then given a special computerized and indestructible car called the Knight Industries Two Thousand (nicknamed KITT), and a mission: apprehend criminals who are beyond the reach of the law. The series depicts Michael's exploits as he and KITT battle the forces of evil on behalf of the Foundation for Law and Government. | E137: 1982 | F137: TV-PG | G137: 00:51 | H137: 51 | I137: ['scifi', 'action', 'crime', 'drama'] | J137: drama | K137: US | L137: ['US'] | M137: 4.0 | N137: tt0083437 | O137: 6.9 | P137: 34115 | Q137: 50.267 | R137: 7.5
A138: ts21715 | B138: Thomas & Friends | C138: SHOW | D138: Thomas & Friends is a British children's television series, which had its first broadcast on the ITV network on 4 September 1984. It is based on The Railway Series of books by the Reverend Wilbert Awdry and his son, Christopher Awdry. These books deal with the adventures of a group of anthropomorphised locomotives and road vehicles who live on the fictional Island of Sodor. The books were based on stories Wilbert told to entertain his son, Christopher during his recovery from measles. From Series one to four, many of the stories are based on events from Awdry's personal experience. | E138: 1984 | F138: TV-Y | G138: 00:10 | H138: 10 | I138: ['animation', 'family', 'comedy', 'fantasy', 'drama', 'action', 'music'] | J138: animation | K138: GB | L138: ['GB'] | M138: 24.0 | N138: tt0086815 | O138: 6.5 | P138: 5104 | Q138: 42.196 | R138: 6.5
A139: ts21715 | B139: Thomas & Friends | C139: SHOW | D139: Thomas & Friends is a British children's television series, which had its first broadcast on the ITV network on 4 September 1984. It is based on The Railway Series of books by the Reverend Wilbert Awdry and his son, Christopher Awdry. These books deal with the adventures of a group of anthropomorphised locomotives and road vehicles who live on the fictional Island of Sodor. The books were based on stories Wilbert told to entertain his son, Christopher during his recovery from measles. From Series one to four, many of the stories are based on events from Awdry's personal experience. | E139: 1984 | F139: TV-Y | G139: 00:10 | H139: 10 | I139: ['animation', 'family', 'comedy', 'fantasy', 'drama', 'action', 'music'] | J139: family | K139: GB | L139: ['GB'] | M139: 24.0 | N139: tt0086815 | O139: 6.5 | P139: 5104 | Q139: 42.196 | R139: 6.5
A140: ts21715 | B140: Thomas & Friends | C140: SHOW | D140: Thomas & Friends is a British children's television series, which had its first broadcast on the ITV network on 4 September 1984. It is based on The Railway Series of books by the Reverend Wilbert Awdry and his son, Christopher Awdry. These books deal with the adventures of a group of anthropomorphised locomotives and road vehicles who live on the fictional Island of Sodor. The books were based on stories Wilbert told to entertain his son, Christopher during his recovery from measles. From Series one to four, many of the stories are based on events from Awdry's personal experience. | E140: 1984 | F140: TV-Y | G140: 00:10 | H140: 10 | I140: ['animation', 'family', 'comedy', 'fantasy', 'drama', 'action', 'music'] | J140: comedy | K140: GB | L140: ['GB'] | M140: 24.0 | N140: tt0086815 | O140: 6.5 | P140: 5104 | Q140: 42.196 | R140: 6.5
A141: ts21715 | B141: Thomas & Friends | C141: SHOW | D141: Thomas & Friends is a British children's television series, which had its first broadcast on the ITV network on 4 September 1984. It is based on The Railway Series of books by the Reverend Wilbert Awdry and his son, Christopher Awdry. These books deal with the adventures of a group of anthropomorphised locomotives and road vehicles who live on the fictional Island of Sodor. The books were based on stories Wilbert told to entertain his son, Christopher during his recovery from measles. From Series one to four, many of the stories are based on events from Awdry's personal experience. | E141: 1984 | F141: TV-Y | G141: 00:10 | H141: 10 | I141: ['animation', 'family', 'comedy', 'fantasy', 'drama', 'action', 'music'] | J141: fantasy | K141: GB | L141: ['GB'] | M141: 24.0 | N141: tt0086815 | O141: 6.5 | P141: 5104 | Q141: 42.196 | R141: 6.5
A142: ts21715 | B142: Thomas & Friends | C142: SHOW | D142: Thomas & Friends is a British children's television series, which had its first broadcast on the ITV network on 4 September 1984. It is based on The Railway Series of books by the Reverend Wilbert Awdry and his son, Christopher Awdry. These books deal with the adventures of a group of anthropomorphised locomotives and road vehicles who live on the fictional Island of Sodor. The books were based on stories Wilbert told to entertain his son, Christopher during his recovery from measles. From Series one to four, many of the stories are based on events from Awdry's personal experience. | E142: 1984 | F142: TV-Y | G142: 00:10 | H142: 10 | I142: ['animation', 'family', 'comedy', 'fantasy', 'drama', 'action', 'music'] | J142: drama | K142: GB | L142: ['GB'] | M142: 24.0 | N142: tt0086815 | O142: 6.5 | P142: 5104 | Q142: 42.196 | R142: 6.5
A143: ts21715 | B143: Thomas & Friends | C143: SHOW | D143: Thomas & Friends is a British children's television series, which had its first broadcast on the ITV network on 4 September 1984. It is based on The Railway Series of books by the Reverend Wilbert Awdry and his son, Christopher Awdry. These books deal with the adventures of a group of anthropomorphised locomotives and road vehicles who live on the fictional Island of Sodor. The books were based on stories Wilbert told to entertain his son, Christopher during his recovery from measles. From Series one to four, many of the stories are based on events from Awdry's personal experience. | E143: 1984 | F143: TV-Y | G143: 00:10 | H143: 10 | I143: ['animation', 'family', 'comedy', 'fantasy', 'drama', 'action', 'music'] | J143: action | K143: GB | L143: ['GB'] | M143: 24.0 | N143: tt0086815 | O143: 6.5 | P143: 5104 | Q143: 42.196 | R143: 6.5
A144: ts21715 | B144: Thomas & Friends | C144: SHOW | D144: Thomas & Friends is a British children's television series, which had its first broadcast on the ITV network on 4 September 1984. It is based on The Railway Series of books by the Reverend Wilbert Awdry and his son, Christopher Awdry. These books deal with the adventures of a group of anthropomorphised locomotives and road vehicles who live on the fictional Island of Sodor. The books were based on stories Wilbert told to entertain his son, Christopher during his recovery from measles. From Series one to four, many of the stories are based on events from Awdry's personal experience. | E144: 1984 | F144: TV-Y | G144: 00:10 | H144: 10 | I144: ['animation', 'family', 'comedy', 'fantasy', 'drama', 'action', 'music'] | J144: music | K144: GB | L144: ['GB'] | M144: 24.0 | N144: tt0086815 | O144: 6.5 | P144: 5104 | Q144: 42.196 | R144: 6.5
A145: ts20678 | B145: Saved by the Bell | C145: SHOW | D145: Lovable schemer Zack Morris leads his pals on adventures at California's Bayside High School. The friends navigate relationships, final exams, school dances, breakups and more while frequently frustrating their principal, Mr. Richard Belding, who does his best to keep them in check. | E145: 1989 | F145: TV-G | G145: 00:23 | H145: 23 | I145: ['family', 'comedy', 'romance'] | J145: family | K145: US | L145: ['US'] | M145: 5.0 | N145: tt0096694 | O145: 7.1 | P145: 35034 | Q145: 19.855 | R145: 8
... A147: ts20678 | B147: Saved by the Bell | C147: SHOW | D147: Lovable schemer Zack Morris leads his pals on adventures at California's Bayside High School. The friends navigate relationships, final exams, school dances, breakups and more while frequently frustrating their principal, Mr. Richard Belding, who does his best to keep them in check. | E147: 1989 | F147: TV-G | G147: 00:23 | H147: 23 | I147: ['family', 'comedy', 'romance'] | J147: romance | K147: US | L147: ['US'] | M147: 5.0 | N147: tt0096694 | O147: 7.1 | P147: 35034 | Q147: 19.855 | R147: 8
A148: tm145608 | B148: Awakenings | C148: MOVIE | D148: Dr. Malcolm Sayer, a shy research physician, uses an experimental drug to "awaken" the catatonic victims of a rare disease. Leonard is the first patient to receive the controversial treatment. His awakening, filled with awe and enthusiasm, proves a rebirth for Sayer too, as the exuberant patient reveals life's simple but unutterably sweet pleasures to the introverted doctor. | E148: 1990 | F148: PG-13 | G148: 02:00 | H148: 120 | I148: ['drama', 'european'] | J148: drama | K148: US | L148: ['US'] | N148: tt0099077 | O148: 7.8 | P148: 139240 | Q148: 12.23 | R148: 7.8
A149: tm145608 | B149: Awakenings | C149: MOVIE | D149: Dr. Malcolm Sayer, a shy research physician, uses an experimental drug to "awaken" the catatonic victims of a rare disease. Leonard is the first patient to receive the controversial treatment. His awakening, filled with awe and enthusiasm, proves a rebirth for Sayer too, as the exuberant patient reveals life's simple but unutterably sweet pleasures to the introverted doctor. | E149: 1990 | F149: PG-13 | G149: 02:00 | H149: 120 | I149: ['drama', 'european'] | J149: european | K149: US | L149: ['US'] | N149: tt0099077 | O149: 7.8 | P149: 139240 | Q149: 12.23 | R149: 7.8
A150: ts25028 | B150: Wheel of Fortune | C150: SHOW | D150: This game show sees contestants solve word puzzles, similar to those used in Hangman, to win cash and prizes determined by spinning a giant carnival wheel. | E150: 1983 | F150: TV-G | G150: 00:26 | H150: 26 | I150: ['family'] | J150: family | K150: US | L150: ['US'] | M150: 39.0 | N150: tt0072584 | O150: 6.7 | P150: 3145 | Q150: 5.935 | R150: 6.8
A151: tm147710 | B151: National Lampoon's Christmas Vacation | C151: MOVIE | D151: It's Christmastime, and the Griswolds are preparing for a family seasonal celebration. But things never run smoothly for Clark, his wife Ellen, and their two kids. Clark's continual bad luck is worsened by his obnoxious family guests, but he manages to keep going, knowing that his Christmas bonus is due soon. | E151: 1989 | F151: PG-13 | G151: 01:37 | H151: 97 | I151: ['comedy', 'european'] | J151: comedy | K151: US | L151: ['US'] | N151: tt0097958 | O151: 7.5 | P151: 185760 | Q151: 18.862 | R151: 7.2
A152: tm147710 | B152: National Lampoon's Christmas Vacation | C152: MOVIE | D152: It's Christmastime, and the Griswolds are preparing for a family seasonal celebration. But things never run smoothly for Clark, his wife Ellen, and their two kids. Clark's continual bad luck is worsened by his obnoxious family guests, but he manages to keep going, knowing that his Christmas bonus is due soon. | E152: 1989 | F152: PG-13 | G152: 01:37 | H152: 97 | I152: ['comedy', 'european'] | J152: european | K152: US | L152: ['US'] | N152: tt0097958 | O152: 7.5 | P152: 185760 | Q152: 18.862 | R152: 7.2
A153: tm142895 | B153: Lean On Me | C153: MOVIE | D153: When principal Joe Clark takes over decaying Eastside High School, he's faced with students wearing gang colors and graffiti-covered walls. Determined to do anything he must to turn the school around, he expels suspected drug dealers, padlocks doors and demands effort and results from students, staff and parents. Autocratic to a fault, this real-life educator put it all on the line. | E153: 1989 | F153: PG-13 | G153: 01:45 | H153: 105 | I153: ['drama'] | J153: drama | K153: US | L153: ['US'] | N153: tt0097722 | O153: 7.4 | P153: 20680 | Q153: 19.449 | R153: 7.3
A154: tm20712 | B154: Eddie Murphy Raw | C154: MOVIE | D154: Eddie Murphy delights, shocks and entertains with dead-on celebrity impersonations, observations on '80s love, sex and marriage, a remembrance of Mom's hamburgers and much more. | E154: 1987 | F154: R | G154: 01:30 | H154: 90 | I154: ['comedy', 'documentation'] | J154: comedy | K154: US | L154: ['US'] | N154: tt0092948 | O154: 7.6 | P154: 19757 | Q154: 7.992 | R154: 7.3
A155: tm20712 | B155: Eddie Murphy Raw | C155: MOVIE | D155: Eddie Murphy delights, shocks and entertains with dead-on celebrity impersonations, observations on '80s love, sex and marriage, a remembrance of Mom's hamburgers and much more. | E155: 1987 | F155: R | G155: 01:30 | H155: 90 | I155: ['comedy', 'documentation'] | J155: documentation | K155: US | L155: ['US'] | N155: tt0092948 | O155: 7.6 | P155: 19757 | Q155: 7.992 | R155: 7.3
A156: tm117580 | B156: She's Gotta Have It | C156: MOVIE | D156: The story of Nola Darling's simultaneous sexual relationships with three different men is told by her and by her partners and other friends. All three men wanted her to commit solely to them; Nola resists being "owned" by a single partner. | E156: 1986 | F156: R | G156: 01:24 | H156: 84 | I156: ['romance', 'comedy'] | J156: romance | K156: US | L156: ['US'] | N156: tt0091939 | O156: 6.7 | P156: 14472 | Q156: 7.416 | R156: 6.707
A157: tm117580 | B157: She's Gotta Have It | C157: MOVIE | D157: The story of Nola Darling's simultaneous sexual relationships with three different men is told by her and by her partners and other friends. All three men wanted her to commit solely to them; Nola resists being "owned" by a single partner. | E157: 1986 | F157: R | G157: 01:24 | H157: 84 | I157: ['romance', 'comedy'] | J157: comedy | K157: US | L157: ['US'] | N157: tt0091939 | O157: 6.7 | P157: 14472 | Q157: 7.416 | R157: 6.707
A158: ts23753 | B158: Major Dad | C158: SHOW | D158: Major Dad is an American sitcom created by Richard C. Okie and John G. Stephens, developed by Earl Pomerantz, that originally ran from 1989 to 1993 on CBS, starring Gerald McRaney as Major John D. MacGillis and Shanna Reed as his wife Polly. The cast also includes Beverly Archer, Matt Mulhern, Jon Cypher, Marisa Ryan, Nicole Dubuc and Chelsea Hertford. | E158: 1989 | F158: TV-PG | G158: 00:24 | H158: 24 | I158: ['comedy', 'family'] | J158: comedy | K158: US | L158: ['US'] | M158: 4.0 | N158: tt0096643 | O158: 6.5 | P158: 2922 | Q158: 9.849 | R158: 6.5
A159: ts23753 | B159: Major Dad | C159: SHOW | D159: Major Dad is an American sitcom created by Richard C. Okie and John G. Stephens, developed by Earl Pomerantz, that originally ran from 1989 to 1993 on CBS, starring Gerald McRaney as Major John D. MacGillis and Shanna Reed as his wife Polly. The cast also includes Beverly Archer, Matt Mulhern, Jon Cypher, Marisa Ryan, Nicole Dubuc and Chelsea Hertford. | E159: 1989 | F159: TV-PG | G159: 00:24 | H159: 24 | I159: ['comedy', 'family'] | J159: family | K159: US | L159: ['US'] | M159: 4.0 | N159: tt0096643 | O159: 6.5 | P159: 2922 | Q159: 9.849 | R159: 6.5
A160: tm130586 | B160: Endless Love | C160: MOVIE | D160: Two young kids fall in love with each other. But the passion is too consuming for the parents of Jade. The parents try to stop them from seeing each other. But when this doesn't work, David burns down the house and is sent away. This doesn't stop him from seeing her. When he gets out he goes to look for her. But the passion for his first love is too strong and she has to leave. | E160: 1981 | F160: R | G160: 01:56 | H160: 116 | I160: ['romance', 'drama'] | J160: romance | K160: US | L160: ['US'] | N160: tt0082329 | O160: 4.9 | P160: 8524 | Q160: 19.116 | R160: 5.7
A161: tm130586 | B161: Endless Love | C161: MOVIE | D161: Two young kids fall in love with each other. But the passion is too consuming for the parents of Jade. The parents try to stop them from seeing each other. But when this doesn't work, David burns down the house and is sent away. This doesn't stop him from seeing her. When he gets out he goes to look for her. But the passion for his first love is too strong and she has to leave. | E161: 1981 | F161: R | G161: 01:56 | H161: 116 | I161: ['romance', 'drama'] | J161: drama | K161: US | L161: ['US'] | N161: tt0082329 | O161: 4.9 | P161: 8524 | Q161: 19.116 | R161: 5.7
A162: ts987 | B162: Danger Mouse | C162: SHOW | D162: Danger Mouse, the world's greatest secret agent, and his side-kick Penfold work to foil the evil schemes of Baron Greenback. | E162: 1981 | F162: TV-Y | G162: 00:14 | H162: 14 | I162: ['animation', 'comedy', 'family', 'scifi', 'european'] | J162: animation | K162: GB | L162: ['GB'] | M162: 10.0 | N162: tt0081848 | O162: 7.4 | P162: 3545 | Q162: 8.55 | R162: 7.5
A163: ts987 | B163: Danger Mouse | C163: SHOW | D163: Danger Mouse, the world's greatest secret agent, and his side-kick Penfold work to foil the evil schemes of Baron Greenback. | E163: 1981 | F163: TV-Y | G163: 00:14 | H163: 14 | I163: ['animation', 'comedy', 'family', 'scifi', 'european'] | J163: comedy | K163: GB | L163: ['GB'] | M163: 10.0 | N163: tt0081848 | O163: 7.4 | P163: 3545 | Q163: 8.55 | R163: 7.5
A164: ts987 | B164: Danger Mouse | C164: SHOW | D164: Danger Mouse, the world's greatest secret agent, and his side-kick Penfold work to foil the evil schemes of Baron Greenback. | E164: 1981 | F164: TV-Y | G164: 00:14 | H164: 14 | I164: ['animation', 'comedy', 'family', 'scifi', 'european'] | J164: family | K164: GB | L164: ['GB'] | M164: 10.0 | N164: tt0081848 | O164: 7.4 | P164: 3545 | Q164: 8.55 | R164: 7.5
A165: ts987 | B165: Danger Mouse | C165: SHOW | D165: Danger Mouse, the world's greatest secret agent, and his side-kick Penfold work to foil the evil schemes of Baron Greenback. | E165: 1981 | F165: TV-Y | G165: 00:14 | H165: 14 | I165: ['animation', 'comedy', 'family', 'scifi', 'european'] | J165: scifi | K165: GB | L165: ['GB'] | M165: 10.0 | N165: tt0081848 | O165: 7.4 | P165: 3545 | Q165: 8.55 | R165: 7.5
A166: ts987 | B166: Danger Mouse | C166: SHOW | D166: Danger Mouse, the world's greatest secret agent, and his side-kick Penfold work to foil the evil schemes of Baron Greenback. | E166: 1981 | F166: TV-Y | G166: 00:14 | H166: 14 | I166: ['animation', 'comedy', 'family', 'scifi', 'european'] | J166: european | K166: GB | L166: ['GB'] | M166: 10.0 | N166: tt0081848 | O166: 7.4 | P166: 3545 | Q166: 8.55 | R166: 7.5
A167: tm721687 | B167: Vaashi | C167: MOVIE | D167: Ebin Mathew, a budding lawyer ambitiously joins hands with his advocate friend Madhavi Mohan, to share a new office space in order for them to start their independent careers. Their relationship gets strained when they land on opposite ends of a case. | E167: 1983 | F167: NO INFORMADO | G167: 02:03 | H167: 123 | I167: ['drama', 'thriller'] | J167: drama | K167: IN | L167: ['IN'] | N167: tt13913068 | O167: 6.7 | P167: 388 | Q167: 3.79
A168: tm721687 | B168: Vaashi | C168: MOVIE | D168: Ebin Mathew, a budding lawyer ambitiously joins hands with his advocate friend Madhavi Mohan, to share a new office space in order for them to start their independent careers. Their relationship gets strained when they land on opposite ends of a case. | E168: 1983 | F168: NO INFORMADO | G168: 02:03 | H168: 123 | I168: ['drama', 'thriller'] | J168: thriller | K168: IN | L168: ['IN'] | N168: tt13913068 | O168: 6.7 | P168: 388 | Q168: 3.79
A169: tm40103 | B169: Mobile Suit Gundam: Char's Counterattack | C169: MOVIE | D169: In UC 0093 the Federation has recovered from its defeat and has created a new anti-colonial special forces unit to deal with rebel forces: Londo Bell. Elsewhere in space Char Aznable re-appears out of self imposed hiding with a declaration that he now commands his own Neo-Zeon movementand intends to force the emigration of Earth's inhabitants to space by bringing about an apocalypse. | E169: 1988 | F169: NO INFORMADO | G169: 01:59 | H169: 119 | I169: ['scifi', 'animation', 'action', 'drama', 'war'] | J169: scifi | K169: JP | L169: ['JP'] | N169: tt0095262 | O169: 7.3 | P169: 1693 | Q169: 8.092 | R169: 6.7
A170: tm40103 | B170: Mobile Suit Gundam: Char's Counterattack | C170: MOVIE | D170: In UC 0093 the Federation has recovered from its defeat and has created a new anti-colonial special forces unit to deal with rebel forces: Londo Bell. Elsewhere in space Char Aznable re-appears out of self imposed hiding with a declaration that he now commands his own Neo-Zeon movementand intends to force the emigration of Earth's inhabitants to space by bringing about an apocalypse. | E170: 1988 | F170: NO INFORMADO | G170: 01:59 | H170: 119 | I170: ['scifi', 'animation', 'action', 'drama', 'war'] | J170: animation | K170: JP | L170: ['JP'] | N170: tt0095262 | O170: 7.3 | P170: 1693 | Q170: 8.092 | R170: 6.7
A171: tm40103 | B171: Mobile Suit Gundam: Char's Counterattack | C171: MOVIE | D171: In UC 0093 the Federation has recovered from its defeat and has created a new anti-colonial special forces unit to deal with rebel forces: Londo Bell. Elsewhere in space Char Aznable re-appears out of self imposed hiding with a declaration that he now commands his own Neo-Zeon movementand intends to force the emigration of Earth's inhabitants to space by bringing about an apocalypse. | E171: 1988 | F171: NO INFORMADO | G171: 01:59 | H171: 119 | I171: ['scifi', 'animation', 'action', 'drama', 'war'] | J171: action | K171: JP | L171: ['JP'] | N171: tt0095262 | O171: 7.3 | P171: 1693 | Q171: 8.092 | R171: 6.7
A172: tm40103 | B172: Mobile Suit Gundam: Char's Counterattack | C172: MOVIE | D172: In UC 0093 the Federation has recovered from its defeat and has created a new anti-colonial special forces unit to deal with rebel forces: Londo Bell. Elsewhere in space Char Aznable re-appears out of self imposed hiding with a declaration that he now commands his own Neo-Zeon movementand intends to force the emigration of Earth's inhabitants to space by bringing about an apocalypse. | E172: 1988 | F172: NO INFORMADO | G172: 01:59 | H172: 119 | I172: ['scifi', 'animation', 'action', 'drama', 'war'] | J172: drama | K172: JP | L172: ['JP'] | N172: tt0095262 | O172: 7.3 | P172: 1693 | Q172: 8.092 | R172: 6.7
A173: tm40103 | B173: Mobile Suit Gundam: Char's Counterattack | C173: MOVIE | D173: In UC 0093 the Federation has recovered from its defeat and has created a new anti-colonial special forces unit to deal with rebel forces: Londo Bell. Elsewhere in space Char Aznable re-appears out of self imposed hiding with a declaration that he now commands his own Neo-Zeon movementand intends to force the emigration of Earth's inhabitants to space by bringing about an apocalypse. | E173: 1988 | F173: NO INFORMADO | G173: 01:59 | H173: 119 | I173: ['scifi', 'animation', 'action', 'drama', 'war'] | J173: war | K173: JP | L173: ['JP'] | N173: tt0095262 | O173: 7.3 | P173: 1693 | Q173: 8.092 | R173: 6.7
A174: tm125985 | B174: Mobile Suit Gundam II: Soldiers of Sorrow | C174: MOVIE | D174: After managing to survive attacks by Zeon's Char Aznable and Garma Zabi, the crew of Federation warship White Base and its mobile suits must battle Zeon forces through Asia, Europe, and the Atlantic Ocean if they are to reach Earth Federation's headquarters alive. During that process many of its crewmembers must overcome their fears, losses, immaturities, and insecurities in order to survive. | E174: 1981 | F174: NO INFORMADO | G174: 02:13 | H174: 133 | I174: ['animation', 'scifi', 'action', 'drama', 'war'] | J174: animation | K174: JP | L174: ['JP'] | N174: tt0159510 | O174: 7.2 | P174: 1274 | Q174: 13.125 | R174: 7.2
A175: tm125985 | B175: Mobile Suit Gundam II: Soldiers of Sorrow | C175: MOVIE | D175: After managing to survive attacks by Zeon's Char Aznable and Garma Zabi, the crew of Federation warship White Base and its mobile suits must battle Zeon forces through Asia, Europe, and the Atlantic Ocean if they are to reach Earth Federation's headquarters alive. During that process many of its crewmembers must overcome their fears, losses, immaturities, and insecurities in order to survive. | E175: 1981 | F175: NO INFORMADO | G175: 02:13 | H175: 133 | I175: ['animation', 'scifi', 'action', 'drama', 'war'] | J175: scifi | K175: JP | L175: ['JP'] | N175: tt0159510 | O175: 7.2 | P175: 1274 | Q175: 13.125 | R175: 7.2
A176: tm125985 | B176: Mobile Suit Gundam II: Soldiers of Sorrow | C176: MOVIE | D176: After managing to survive attacks by Zeon's Char Aznable and Garma Zabi, the crew of Federation warship White Base and its mobile suits must battle Zeon forces through Asia, Europe, and the Atlantic Ocean if they are to reach Earth Federation's headquarters alive. During that process many of its crewmembers must overcome their fears, losses, immaturities, and insecurities in order to survive. | E176: 1981 | F176: NO INFORMADO | G176: 02:13 | H176: 133 | I176: ['animation', 'scifi', 'action', 'drama', 'war'] | J176: action | K176: JP | L176: ['JP'] | N176: tt0159510 | O176: 7.2 | P176: 1274 | Q176: 13.125 | R176: 7.2
A177: tm125985 | B177: Mobile Suit Gundam II: Soldiers of Sorrow | C177: MOVIE | D177: After managing to survive attacks by Zeon's Char Aznable and Garma Zabi, the crew of Federation warship White Base and its mobile suits must battle Zeon forces through Asia, Europe, and the Atlantic Ocean if they are to reach Earth Federation's headquarters alive. During that process many of its crewmembers must overcome their fears, losses, immaturities, and insecurities in order to survive. | E177: 1981 | F177: NO INFORMADO | G177: 02:13 | H177: 133 | I177: ['animation', 'scifi', 'action', 'drama', 'war'] | J177: drama | K177: JP | L177: ['JP'] | N177: tt0159510 | O177: 7.2 | P177: 1274 | Q177: 13.125 | R177: 7.2
A178: tm125985 | B178: Mobile Suit Gundam II: Soldiers of Sorrow | C178: MOVIE | D178: After managing to survive attacks by Zeon's Char Aznable and Garma Zabi, the crew of Federation warship White Base and its mobile suits must battle Zeon forces through Asia, Europe, and the Atlantic Ocean if they are to reach Earth Federation's headquarters alive. During that process many of its crewmembers must overcome their fears, losses, immaturities, and insecurities in order to survive. | E178: 1981 | F178: NO INFORMADO | G178: 02:13 | H178: 133 | I178: ['animation', 'scifi', 'action', 'drama', 'war'] | J178: war | K178: JP | L178: ['JP'] | N178: tt0159510 | O178: 7.2 | P178: 1274 | Q178: 13.125 | R178: 7.2
A179: ts2760 | B179: Fireman Sam | C179: SHOW | D179: Follow the adventures of fireman Sam and his colleagues as they protect the citizens of the Welsh town of Pontypandy. Whenever the alarm sounds, brave Sam and his co-workers can be counted on to jump into a fire engine, hop onto a helicopter, or even launch an inflatable lifeboat to battle blazes, mount rescue missions, or provide medical attention to those in need. | E179: 1987 | F179: TV-Y | G179: 00:10 | H179: 10 | I179: ['animation', 'comedy', 'family', 'crime', 'european'] | J179: animation | K179: GB | L179: ['GB'] | M179: 13.0 | N179: tt0329829 | O179: 6.1 | P179: 1785 | Q179: 37.647 | R179: 7.2
A180: ts2760 | B180: Fireman Sam | C180: SHOW | D180: Follow the adventures of fireman Sam and his colleagues as they protect the citizens of the Welsh town of Pontypandy. Whenever the alarm sounds, brave Sam and his co-workers can be counted on to jump into a fire engine, hop onto a helicopter, or even launch an inflatable lifeboat to battle blazes, mount rescue missions, or provide medical attention to those in need. | E180: 1987 | F180: TV-Y | G180: 00:10 | H180: 10 | I180: ['animation', 'comedy', 'family', 'crime', 'european'] | J180: comedy | K180: GB | L180: ['GB'] | M180: 13.0 | N180: tt0329829 | O180: 6.1 | P180: 1785 | Q180: 37.647 | R180: 7.2
A181: ts2760 | B181: Fireman Sam | C181: SHOW | D181: Follow the adventures of fireman Sam and his colleagues as they protect the citizens of the Welsh town of Pontypandy. Whenever the alarm sounds, brave Sam and his co-workers can be counted on to jump into a fire engine, hop onto a helicopter, or even launch an inflatable lifeboat to battle blazes, mount rescue missions, or provide medical attention to those in need. | E181: 1987 | F181: TV-Y | G181: 00:10 | H181: 10 | I181: ['animation', 'comedy', 'family', 'crime', 'european'] | J181: family | K181: GB | L181: ['GB'] | M181: 13.0 | N181: tt0329829 | O181: 6.1 | P181: 1785 | Q181: 37.647 | R181: 7.2
A182: ts2760 | B182: Fireman Sam | C182: SHOW | D182: Follow the adventures of fireman Sam and his colleagues as they protect the citizens of the Welsh town of Pontypandy. Whenever the alarm sounds, brave Sam and his co-workers can be counted on to jump into a fire engine, hop onto a helicopter, or even launch an inflatable lifeboat to battle blazes, mount rescue missions, or provide medical attention to those in need. | E182: 1987 | F182: TV-Y | G182: 00:10 | H182: 10 | I182: ['animation', 'comedy', 'family', 'crime', 'european'] | J182: crime | K182: GB | L182: ['GB'] | M182: 13.0 | N182: tt0329829 | O182: 6.1 | P182: 1785 | Q182: 37.647 | R182: 7.2
A183: ts2760 | B183: Fireman Sam | C183: SHOW | D183: Follow the adventures of fireman Sam and his colleagues as they protect the citizens of the Welsh town of Pontypandy. Whenever the alarm sounds, brave Sam and his co-workers can be counted on to jump into a fire engine, hop onto a helicopter, or even launch an inflatable lifeboat to battle blazes, mount rescue missions, or provide medical attention to those in need. | E183: 1987 | F183: TV-Y | G183: 00:10 | H183: 10 | I183: ['animation', 'comedy', 'family', 'crime', 'european'] | J183: european | K183: GB | L183: ['GB'] | M183: 13.0 | N183: tt0329829 | O183: 6.1 | P183: 1785 | Q183: 37.647 | R183: 7.2
A184: tm21953 | B184: Sam Kinison: Breaking the Rules | C184: MOVIE | D184: This is a great performance. Through yelling and energetic story-telling, he talks about marriage, drugs, being arrested (thanks to his ex-wife), pleasing women, religion, and much, much more. | E184: 1987 | F184: R | G184: 00:50 | H184: 50 | I184: ['comedy', 'documentation'] | J184: comedy | K184: US | L184: ['US'] | N184: tt0307403 | O184: 7.2 | P184: 660 | Q184: 1.843 | R184: 7.2
A185: tm21953 | B185: Sam Kinison: Breaking the Rules | C185: MOVIE | D185: This is a great performance. Through yelling and energetic story-telling, he talks about marriage, drugs, being arrested (thanks to his ex-wife), pleasing women, religion, and much, much more. | E185: 1987 | F185: R | G185: 00:50 | H185: 50 | I185: ['comedy', 'documentation'] | J185: documentation | K185: US | L185: ['US'] | N185: tt0307403 | O185: 7.2 | P185: 660 | Q185: 1.843 | R185: 7.2
A186: tm126769 | B186: Waiting for the Hearse | C186: MOVIE | D186: Mama Cora, who is almost eighty years old, has three sons and a daughter. She lives with one of them, who has serious financial problems. The family meets one day to celebrate an anniversary meal, and that is when the problem arises: which of them will take care of her? | E186: 1985 | F186: NO INFORMADO | G186: 01:27 | H186: 87 | I186: ['comedy'] | J186: comedy | K186: AR | L186: ['AR'] | N186: tt0089108 | O186: 8 | P186: 6399 | Q186: 7.81 | R186: 8.1
A187: tm152839 | B187: Tim Allen: Men Are Pigs | C187: MOVIE | D187: Comedian Tim Allen shares his enthusiasm for power tools, automobiles, grunting, and the myriad obsessions of the American male in this special for the Showtime premium cable network, which was aired a few years before he rose to stardom with the television sitcom Home Improvement. | E187: 1990 | F187: NO INFORMADO | G187: 00:30 | H187: 30 | I187: ['comedy', 'documentation'] | J187: comedy | K187: US | L187: ['US'] | N187: tt0259057 | O187: 6.1 | P187: 360 | Q187: 2.482 | R187: 6.3
A188: tm152839 | B188: Tim Allen: Men Are Pigs | C188: MOVIE | D188: Comedian Tim Allen shares his enthusiasm for power tools, automobiles, grunting, and the myriad obsessions of the American male in this special for the Showtime premium cable network, which was aired a few years before he rose to stardom with the television sitcom Home Improvement. | E188: 1990 | F188: NO INFORMADO | G188: 00:30 | H188: 30 | I188: ['comedy', 'documentation'] | J188: documentation | K188: US | L188: ['US'] | N188: tt0259057 | O188: 6.1 | P188: 360 | Q188: 2.482 | R188: 6.3
A189: tm49037 | B189: Mobile Suit Gundam III: Encounters in Space | C189: MOVIE | D189: Amuro Ray and the rest of the White Base crew, now denominated the 13th Autonomous Corps, return to outer space to support the rest of the Earth Federation forces for the decisive battle against the Duchy of Zeon's forces. | E189: 1982 | F189: NO INFORMADO | G189: 02:24 | H189: 144 | I189: ['action', 'drama', 'war', 'animation', 'scifi'] | J189: action | K189: JP | L189: ['JP'] | N189: tt0159511 | O189: 7.6 | P189: 1236 | Q189: 12.741 | R189: 7.5
A190: tm49037 | B190: Mobile Suit Gundam III: Encounters in Space | C190: MOVIE | D190: Amuro Ray and the rest of the White Base crew, now denominated the 13th Autonomous Corps, return to outer space to support the rest of the Earth Federation forces for the decisive battle against the Duchy of Zeon's forces. | E190: 1982 | F190: NO INFORMADO | G190: 02:24 | H190: 144 | I190: ['action', 'drama', 'war', 'animation', 'scifi'] | J190: drama | K190: JP | L190: ['JP'] | N190: tt0159511 | O190: 7.6 | P190: 1236 | Q190: 12.741 | R190: 7.5
...

Sheet Tablas dinámicas
A3: Títulos | B3: IMDb medio | C3: TMDb medio | D3: Popularidad media | E3: Duración media
A4: 5577 | B4: 6.5179645 | C4: 6.8318808 | D4: 23.146124 | E4: 77.861036
A9: Etiquetas de fila | B9: Títulos
A10: MOVIE | B10: 3561
A11: SHOW | B11: 2016
A12: Total general | B12: 5577
B15: Títulos | D15: Etiquetas de fila | E15: Títulos | F15: Etiquetas de fila | G15: Títulos | H15: Etiquetas de fila | I15: Títulos | J15: Etiquetas de fila | K15: Títulos | O15: Etiquetas de fila | P15: Títulos | U15: Etiquetas de fila | V15: Duración media | W15: IMDb medio | X15: Votos IMDb | Y15: Temporadas
A16: 2012 | B16: 106 | D16: drama | E16: 2927 | F16: US | G16: 2303 | H16: G | I16: 110 | J16: 1 Infantil | K16: 207 | O16: Excelente | P16: 479 | U16: Breaking Bad | V16: 48 | W16: 9.5 | X16: 1775990 | Y16: 3
A17: 2013 | B17: 130 | D17: comedy | E17: 2235 | F17: IN | G17: 621 | H17: NC-17 | I17: 16 | J17: 2 Familiar | K17: 592 | O17: Muy buena | P17: 1539 | U17: Our Planet | V17: 50 | W17: 9.3 | X17: 42259 | Y17: 1
A18: 2014 | B18: 150 | D18: thriller | E18: 1213 | F18: GB | G18: 404 | H18: NO INFORMADO | I18: 2442 | J18: 3 Adolescentes | K18: 904 | O18: Buena | P18: 1699 | U18: Avatar: The Last Airbender | V18: 24 | W18: 9.3 | X18: 303666 | Y18: 5
A19: 2015 | B19: 218 | D19: action | E19: 1143 | F19: JP | G19: 282 | H19: PG | I19: 230 | J19: 4 Adultos | K19: 550 | O19: Regular | P19: 1003 | U19: Reply 1988 | V19: 92 | W19: 9.2 | X19: 6718 | Y19: 4
A20: 2016 | B20: 360 | D20: romance | E20: 959 | F20: FR | G20: 247 | H20: PG-13 | I20: 444 | J20: 5 Adultos con reparos | K20: 882 | O20: Baja | P20: 468 | U20: Kota Factory | V20: 39 | W20: 9.1 | X20: 69316 | Y20: 2
A21: 2017 | B21: 551 | D21: crime | E21: 925 | F21: KR | G21: 222 | H21: R | I21: 550 | J21: 6 Sin clasificar | K21: 2442 | O21: Sin valoración | P21: 389
A22: 2018 | B22: 741 | D22: documentation | E22: 898 | F22: CA | G22: 216 | H22: TV-14 | I22: 460 | J22: Total general | K22: 5577
A23: 2019 | B23: 790 | D23: animation | E23: 657 | F23: ES | G23: 210 | H23: TV-G | I23: 77
A24: 2020 | B24: 757 | D24: family | E24: 655 | F24: DE | G24: 139 | H24: TV-MA | I24: 866
A25: 2021 | B25: 726 | D25: fantasy | E25: 622 | F25: MX | G25: 126 | H25: TV-PG | I25: 175
A26: 2022 | B26: 336 | D26: scifi | E26: 581 | F26: CN | G26: 102 | H26: TV-Y | I26: 95
A27: Total general | B27: 4865 | D27: european | E27: 443 | F27: BR | G27: 101 | H27: TV-Y7 | I27: 112
D28: horror | E28: 373 | F28: PH | G28: 86 | H28: Total general | I28: 5577
D29: music | E29: 251 | F29: TR | G29: 84
D30: history | E30: 250 | F30: AU | G30: 84
D31: reality | E31: 216 | F31: IT | G31: 83
D32: sport | E32: 169 | F32: NG | G32: 73
D33: war | E33: 163 | F33: AR | G33: 72
D34: western | E34: 41 | F34: TW | G34: 64
D35: Total general | E35: 5577 | F35: ID | G35: 62

Sheet DASHBOARD
A1: CLASIFICACIÓN
A13: VALORACIÓN
J16: TITULO | K16: DUR. | L16: IMDB | M16: VOTOS | N16: TEMP.
I17: 1 | J17: ='Tablas dinámicas'!U16 -> Breaking Bad | K17: ='Tablas dinámicas'!V16 -> 48 | L17: ='Tablas dinámicas'!W16 -> 9.5 | M17: ='Tablas dinámicas'!X16 -> 1775990 | N17: ='Tablas dinámicas'!Y16 -> 3
I18: 2 | J18: ='Tablas dinámicas'!U17 -> Our Planet | K18: ='Tablas dinámicas'!V17 -> 50 | L18: ='Tablas dinámicas'!W17 -> 9.3 | M18: ='Tablas dinámicas'!X17 -> 42259 | N18: ='Tablas dinámicas'!Y17 -> 1
I19: 3 | J19: ='Tablas dinámicas'!U18 -> Avatar: The Last Airbender | K19: ='Tablas dinámicas'!V18 -> 24 | L19: ='Tablas dinámicas'!W18 -> 9.3 | M19: ='Tablas dinámicas'!X18 -> 303666 | N19: ='Tablas dinámicas'!Y18 -> 5
I20: 4 | J20: ='Tablas dinámicas'!U19 -> Reply 1988 | K20: ='Tablas dinámicas'!V19 -> 92 | L20: ='Tablas dinámicas'!W19 -> 9.2 | M20: ='Tablas dinámicas'!X19 -> 6718 | N20: ='Tablas dinámicas'!Y19 -> 4
I21: 5 | J21: ='Tablas dinámicas'!U20 -> Kota Factory | K21: ='Tablas dinámicas'!V20 -> 39 | L21: ='Tablas dinámicas'!W20 -> 9.1 | M21: ='Tablas dinámicas'!X20 -> 69316 | N21: ='Tablas dinámicas'!Y20 -> 2
A26: GENERO

Sheet encabezados
A1: id
A2: title
A3: type
A4: description
A5: release_year
A6: age_certification
A7: runtime_HHMM
A8: runtime
A9: genres
A10: genres - Clean
A11: production_countries - Clean
A12: production_countries
... A19: seasons_clean

Sheet DIMENSIONES
A1: IMDb_Tier_Filtro
A2: Excelente
A3: Muy buena
A4: Buena
A5: Regular
A6: Baja
